verysimple/__init__.py
verysimple/add.py
verysimple/minus.py
verysimple/extras/__init__.py
verysimple/extras/multiply.py
verysimple1/__init__.py
verysimple1/add.py
verysimple1/minus.py
verysimple1/extras/__init__.py
verysimple1/extras/multiply.py
verysimple23/__init__.py
verysimple23/add.py
verysimple23/minus.py
verysimple23/extras/__init__.py
verysimple23/extras/multiply.py
verysimple23-0.11.dist-info/METADATA
verysimple23-0.11.dist-info/WHEEL
verysimple23-0.11.dist-info/top_level.txt
verysimple23-0.11.dist-info/RECORD
